fintz/__init__.py
fintz/_base.py
fintz/_bolsa.py
fintz/_tesouro.py
fintz-0.0.4.dist-info/METADATA
fintz-0.0.4.dist-info/WHEEL
fintz-0.0.4.dist-info/RECORD
