Metadata-Version: 2.1
Name: fintz
Version: 0.0.4
Summary: Python client to interact with Fintz API
Author: João Vicente Meyer
Author-email: 1994meyer@gmail.com
Requires-Python: >=3.8,<4.0
Classifier: Programming Language :: Python :: 3
Classifier: Programming Language :: Python :: 3.8
Classifier: Programming Language :: Python :: 3.9
Classifier: Programming Language :: Python :: 3.10
Classifier: Programming Language :: Python :: 3.11
Requires-Dist: httpx (>=0.23.3,<0.24.0)
